{
	"data": [
		{"id":"0","width":250,"height":400,"download_url":"https://picsum.photos/id/0/250/400"},
		{"id":"15","width":250,"height":400,"download_url":"https://picsum.photos/id/15/250/400"},
		{"id":"25","width":250,"height":400,"download_url":"https://picsum.photos/id/25/250/400"},
		{"id":"50","width":250,"height":400,"download_url":"https://picsum.photos/id/10/250/400"},
		{"id":"75","width":250,"height":400,"download_url":"https://picsum.photos/id/75/250/400"},
		{"id":"100","width":250,"height":400,"download_url":"https://picsum.photos/id/100/250/400"},
		{"id":"250","width":250,"height":400,"download_url":"https://picsum.photos/id/250/250/400"},
		{"id":"350","width":250,"height":400,"download_url":"https://picsum.photos/id/350/250/400"},
		{"id":"450","width":250,"height":400,"download_url":"https://picsum.photos/id/450/250/400"},
		{"id":"550","width":250,"height":400,"download_url":"https://picsum.photos/id/550/250/400"},
		{"id":"650","width":250,"height":400,"download_url":"https://picsum.photos/id/650/250/400"},
		{"id":"790","width":250,"height":400,"download_url":"https://picsum.photos/id/790/250/400"},
		{"id":"810","width":250,"height":400,"download_url":"https://picsum.photos/id/810/250/400"},
		{"id":"950","width":250,"height":400,"download_url":"https://picsum.photos/id/950/250/400"},
		{"id":"1000","width":250,"height":400,"download_url":"https://picsum.photos/id/1000/250/400"},
		{"id":"1001","width":250,"height":400,"download_url":"https://picsum.photos/id/1001/250/400"}
	],
	"data1": [
		{"id":"0","width":250,"height":400,"download_url":"https://picsum.photos/id/0/250/400"},
		{"id":"15","width":250,"height":400,"download_url":"https://picsum.photos/id/15/250/400"},
		{"id":"50","width":250,"height":400,"download_url":"https://picsum.photos/id/10/250/400"},
		{"id":"75","width":250,"height":400,"download_url":"https://picsum.photos/id/75/250/400"},
		{"id":"250","width":250,"height":400,"download_url":"https://picsum.photos/id/250/250/400"},
		{"id":"350","width":250,"height":400,"download_url":"https://picsum.photos/id/350/250/400"},
		{"id":"550","width":250,"height":400,"download_url":"https://picsum.photos/id/550/250/400"},
		{"id":"650","width":250,"height":400,"download_url":"https://picsum.photos/id/650/250/400"},		
		{"id":"810","width":250,"height":400,"download_url":"https://picsum.photos/id/810/250/400"},
		{"id":"950","width":250,"height":400,"download_url":"https://picsum.photos/id/950/250/400"},		
		{"id":"1001","width":250,"height":400,"download_url":"https://picsum.photos/id/1001/250/400"}
	],
	"data2": [
		{"id":"0","width":250,"height":400,"download_url":"https://picsum.photos/id/0/250/400"},		
		{"id":"25","width":250,"height":400,"download_url":"https://picsum.photos/id/25/250/400"},
		{"id":"50","width":250,"height":400,"download_url":"https://picsum.photos/id/10/250/400"},		
		{"id":"100","width":250,"height":400,"download_url":"https://picsum.photos/id/100/250/400"},
		{"id":"250","width":250,"height":400,"download_url":"https://picsum.photos/id/250/250/400"},
		{"id":"450","width":250,"height":400,"download_url":"https://picsum.photos/id/450/250/400"},
		{"id":"550","width":250,"height":400,"download_url":"https://picsum.photos/id/550/250/400"},
		{"id":"790","width":250,"height":400,"download_url":"https://picsum.photos/id/790/250/400"},
		{"id":"810","width":250,"height":400,"download_url":"https://picsum.photos/id/810/250/400"},
		{"id":"1000","width":250,"height":400,"download_url":"https://picsum.photos/id/1000/250/400"},
		{"id":"1001","width":250,"height":400,"download_url":"https://picsum.photos/id/1001/250/400"}
	]
}